django_jira/__init__.py
django_jira/error_handler/__init__.py
django_jira/error_handler/drf_handler.py
django_jira/error_handler/templates/__init__.py
django_jira/error_handler/templates/drf_error_template.md
django_jira/tasks/__init__.py
django_jira/tasks/tasks.py
django_jira-0.2.6.dist-info/WHEEL
django_jira-0.2.6.dist-info/METADATA
django_jira-0.2.6.dist-info/RECORD
